comiccompiler/__init__.py
comiccompiler/arguments.py
comiccompiler/comgui.py
comiccompiler/compiler.py
comiccompiler/downloader.py
comiccompiler/entities.py
comiccompiler/imgmag.py
comiccompiler/localfiles.py
comiccompiler/logger.py
comiccompiler/version.py
comiccompiler/waifu.py
comiccompiler/resources/pow_icon.ico
comicom-1.3.1.data/scripts/cc-suite.py
comicom-1.3.1.data/scripts/comgui-launcher.py
comicom-1.3.1.data/scripts/comicom.py
comicom-1.3.1.dist-info/LICENSE
comicom-1.3.1.dist-info/METADATA
comicom-1.3.1.dist-info/WHEEL
comicom-1.3.1.dist-info/top_level.txt
comicom-1.3.1.dist-info/RECORD
