Metadata-Version: 2.1
Name: comicom
Version: 1.3.1
Summary: A script that stitches images together and breaks them in to pages based on available whitespace
Home-page: https://github.com/bajuwa/ComicCompiler
Author: bajuwa
Author-email: justcallmebaj@gmail.com
License: UNKNOWN
Platform: UNKNOWN
Classifier: Programming Language :: Python :: 3
Classifier: Operating System :: OS Independent
Requires-Dist: requests
Requires-Dist: natsort
Requires-Dist: pillow
